{"inkVersion":20,"root":[["^I see our warnings to leave this place have once again been ignored. Fine, wanderer - if you wish so desperately to test Selandris’ resolve, then so be it!",{"#":"druid"},"\n","ev","str","^Fight!","/str","/ev",{"*":"0.c-0","flg":4},{"c-0":["\n","^>>>COMBAT:Starlit Ritualist","\n",{"->":"0.combat"},{"#f":5}],"combat":["^No! The ritual will not be- disturbed...",{"#":"druid"},"\n","ev","str","^What Ritual?","/str","/ev",{"*":".^.c-1","flg":4},{"c-1":["\n","^>>>>ADDEVENTS:Ghostclaw Howler:2","\n","^The hour of Selandris' twilight is nigh, wanderer - not even the Guardian could stop us now...",{"#":"druid"},"\n","^>>>>RELOADEVENTS","\n","end",{"->":"0.g-0"},{"#f":5}],"#f":5}],"g-0":["done",{"#f":5}]}],"done",{"#f":1}],"listDefs":{}}